crosslingual_coreference/CorefResolver.py
crosslingual_coreference/CrossLingualPredictor.py
crosslingual_coreference/CrossLingualPredictorSpacy.py
crosslingual_coreference/__init__.py
crosslingual_coreference/examples/__init__.py
crosslingual_coreference/examples/data.py
crosslingual_coreference/examples/test_chunking.py
crosslingual_coreference/examples/test_individual.py
crosslingual_coreference/examples/test_spacy.py
crosslingual_coreference-0.3.1.dist-info/entry_points.txt
crosslingual_coreference-0.3.1.dist-info/LICENSE
crosslingual_coreference-0.3.1.dist-info/WHEEL
crosslingual_coreference-0.3.1.dist-info/METADATA
crosslingual_coreference-0.3.1.dist-info/RECORD
