Metadata-Version: 2.1
Name: crosslingual-coreference
Version: 0.3.1
Summary: A multi-lingual approach to AllenNLP CoReference Resolution, along with a wrapper for spaCy.
Home-page: https://github.com/pandora-intelligence/crosslingual-coreference
License: MIT
Keywords: AllenNLP,spaCy,NLP
Author: David Berenstein
Author-email: david.m.berenstein@gmail.com
Requires-Python: >=3.8,<3.12
Classifier: Intended Audience :: Developers
Classifier: Intended Audience :: Science/Research
Classifier: License :: OSI Approved :: MIT License
Classifier: Operating System :: OS Independent
Classifier: Programming Language :: Python :: 3
Classifier: Programming Language :: Python :: 3.8
Classifier: Programming Language :: Python :: 3.9
Classifier: Programming Language :: Python :: 3.10
Classifier: Programming Language :: Python :: 3.10
Classifier: Programming Language :: Python :: 3.11
Classifier: Programming Language :: Python :: 3.8
Classifier: Programming Language :: Python :: 3.9
Classifier: Topic :: Scientific/Engineering
Classifier: Topic :: Software Development
Requires-Dist: allennlp (>=2.9,<2.10)
Requires-Dist: allennlp-models (>=2.9,<2.10)
Requires-Dist: cached-path (==1.1.2)
Requires-Dist: protobuf (>=3.20,<4.0)
Requires-Dist: scipy (>=1.7,<2.0)
Requires-Dist: spacy (>=3.1,<3.2)
Project-URL: Documentation, https://github.com/pandora-intelligence/crosslingual-coreference
Project-URL: Repository, https://github.com/pandora-intelligence/crosslingual-coreference
